hooks/__init__.py
hooks/check_untracked_migrations.py
hooks/po_location_format.py
hooks/utils.py
pre_commit_hooks_django-0.4.0.dist-info/LICENSE
pre_commit_hooks_django-0.4.0.dist-info/METADATA
pre_commit_hooks_django-0.4.0.dist-info/WHEEL
pre_commit_hooks_django-0.4.0.dist-info/entry_points.txt
pre_commit_hooks_django-0.4.0.dist-info/top_level.txt
pre_commit_hooks_django-0.4.0.dist-info/RECORD
